[
    {
        "id": 1,
        "name": "Jake Allvsky",
        "stats": [
            {
                "name": "code",
                "rank": 5
            },
            {
                "name": "art",
                "rank": 5
            }
        ]
    },
    {
        "id": 2,
        "name": "Jake 2",
        "stats": [
            {
                "name": "code",
                "rank": 5
            },
            {
                "name": "art",
                "rank": 5
            }
        ]
    }
]